nap/__init__.py
nap/url.py
nap-2.0.0.dist-info/DESCRIPTION.rst
nap-2.0.0.dist-info/METADATA
nap-2.0.0.dist-info/pydist.json
nap-2.0.0.dist-info/RECORD
nap-2.0.0.dist-info/top_level.txt
nap-2.0.0.dist-info/WHEEL
