Metadata-Version: 2.0
Name: nap
Version: 2.0.0
Summary: Convenient way to request HTTP APIs
Home-page: https://github.com/kimmobrunfeldt/nap
Author: Kimmo Brunfeldt
Author-email: kimmobrunfeldt@gmail.com
License: MIT
Keywords: nap rest requests http
Platform: UNKNOWN
Classifier: Development Status :: 4 - Beta
Classifier: Intended Audience :: Developers
Classifier: License :: OSI Approved :: MIT License
Classifier: Natural Language :: English
Classifier: Programming Language :: Python :: 2
Classifier: Programming Language :: Python :: 2.6
Classifier: Programming Language :: Python :: 2.7
Classifier: Programming Language :: Python :: 3
Classifier: Programming Language :: Python :: 3.2
Classifier: Programming Language :: Python :: 3.3
Classifier: Programming Language :: Python :: 3.4
Classifier: Programming Language :: Python :: Implementation :: PyPy
Requires-Dist: requests (>=2.2.1,<3.0.0)
